terrario/__init__.py
terrario/__main__.py
terrario/button.py
terrario/constants.py
terrario/game.py
terrario/map.py
terrario/menu.py
terrario/player.py
terrario/prop.py
terrario/saving.py
terrario/textures.py
terrario/tile.py
terrario/fonts/prstart.ttf
terrario/images/button/button_hovered.png
terrario/images/button/delete_button.png
terrario/images/button/delete_button_hovered.png
terrario/images/button/p_button.png
terrario/images/button/up_button.png
terrario/images/button/world_button.png
terrario/images/button/world_button_hovered.png
terrario/images/button/x_mark.png
terrario/images/button/x_mark_hovered.png
terrario/images/ores/coal.png
terrario/images/ores/copper.png
terrario/images/ores/dark_crystal.png
terrario/images/ores/gold.png
terrario/images/ores/iron.png
terrario/images/ores/rock.png
terrario/images/ores/ruby.png
terrario/images/ores/soul.png
terrario/images/ores/uranium.png
terrario/images/player/drill_down.png
terrario/images/player/drill_left.png
terrario/images/player/drill_right.png
terrario/images/player/drill_up.png
terrario/images/player/drilltip_down_1.png
terrario/images/player/drilltip_down_2.png
terrario/images/player/drilltip_down_3.png
terrario/images/player/drilltip_down_4.png
terrario/images/player/drilltip_down_5.png
terrario/images/player/drilltip_down_6.png
terrario/images/player/drilltip_down_7.png
terrario/images/player/drilltip_left_1.png
terrario/images/player/drilltip_left_2.png
terrario/images/player/drilltip_left_3.png
terrario/images/player/drilltip_left_4.png
terrario/images/player/drilltip_left_5.png
terrario/images/player/drilltip_left_6.png
terrario/images/player/drilltip_left_7.png
terrario/images/player/drilltip_right_1.png
terrario/images/player/drilltip_right_2.png
terrario/images/player/drilltip_right_3.png
terrario/images/player/drilltip_right_4.png
terrario/images/player/drilltip_right_5.png
terrario/images/player/drilltip_right_6.png
terrario/images/player/drilltip_right_7.png
terrario-1.0.1.dist-info/LICENSE
terrario-1.0.1.dist-info/METADATA
terrario-1.0.1.dist-info/WHEEL
terrario-1.0.1.dist-info/entry_points.txt
terrario-1.0.1.dist-info/top_level.txt
terrario-1.0.1.dist-info/RECORD
