Metadata-Version: 2.1
Name: terrario
Version: 1.0.1
Summary: A 2D mining game made with Pygame.
Author-email: MaitreRenard18 <maitre.renardowo@gmail.com>
License: GNU GENERAL PUBLIC LICENSE
Project-URL: Homepage, https://github.com/MaitreRenard18/Terrario-2
Project-URL: Bug Tracker, https://github.com/MaitreRenard18/Terrario-2/issues
Classifier: Programming Language :: Python :: 3
Classifier: License :: OSI Approved :: GNU General Public License v3 (GPLv3)
Classifier: Operating System :: OS Independent
Requires-Python: >=3.6
License-File: LICENSE
Requires-Dist: pygame >=2.1.1
Requires-Dist: opensimplex
